parsebrologs/__init__.py
parsebrologs-1.1.4.dist-info/METADATA
parsebrologs-1.1.4.dist-info/RECORD
parsebrologs-1.1.4.dist-info/WHEEL
parsebrologs-1.1.4.dist-info/top_level.txt
