Metadata-Version: 2.1
Name: parsebrologs
Version: 1.1.4
Summary: A lightweight utility for programmatically reading and manipulating Bro IDS log files and outputting into JSON or CSV format.
Home-page: https://github.com/dgunter/parsebrologs
Author: Dan Gunter
Author-email: dangunter@gmail.com
License: UNKNOWN
Download-URL: https://github.com/dgunter/ParseBroLogs/archive/v1.1.4.tar.gz
Keywords: InfoSec,Bro IDS,security
Platform: UNKNOWN
Classifier: Programming Language :: Python :: 3
Classifier: License :: OSI Approved :: MIT License
Classifier: Operating System :: OS Independent
Classifier: Topic :: Security
